causalml-0.15.5.dist-info/RECORD
causalml-0.15.5.dist-info/WHEEL
causalml-0.15.5.dist-info/top_level.txt
causalml-0.15.5.dist-info/METADATA
causalml-0.15.5.dist-info/licenses/LICENSE
causalml/propensity.py
causalml/__init__.py
causalml/features.py
causalml/match.py
causalml/metrics/regression.py
causalml/metrics/classification.py
causalml/metrics/__init__.py
causalml/metrics/visualize.py
causalml/metrics/sensitivity.py
causalml/metrics/const.py
causalml/optimize/pns.py
causalml/optimize/value_optimization.py
causalml/optimize/__init__.py
causalml/optimize/utils.py
causalml/optimize/policylearner.py
causalml/optimize/unit_selection.py
causalml/dataset/synthetic.py
causalml/dataset/regression.py
causalml/dataset/classification.py
causalml/dataset/__init__.py
causalml/feature_selection/__init__.py
causalml/feature_selection/filters.py
causalml/inference/__init__.py
causalml/inference/tree/uplift.c
causalml/inference/tree/uplift.cpython-311-darwin.so
causalml/inference/tree/plot.py
causalml/inference/tree/__init__.py
causalml/inference/tree/utils.py
causalml/inference/tree/uplift.pyx
causalml/inference/tree/_tree/_utils.pyx
causalml/inference/tree/_tree/_tree.pxd
causalml/inference/tree/_tree/_utils.cpython-311-darwin.so
causalml/inference/tree/_tree/_tree.cpp
causalml/inference/tree/_tree/_criterion.pyx
causalml/inference/tree/_tree/_typedefs.pxd
causalml/inference/tree/_tree/_splitter.pyx
causalml/inference/tree/_tree/__init__.py
causalml/inference/tree/_tree/_splitter.cpython-311-darwin.so
causalml/inference/tree/_tree/_criterion.cpp
causalml/inference/tree/_tree/_splitter.pxd
causalml/inference/tree/_tree/_typedefs.pyx
causalml/inference/tree/_tree/_criterion.pxd
causalml/inference/tree/_tree/_splitter.cpp
causalml/inference/tree/_tree/_tree.cpython-311-darwin.so
causalml/inference/tree/_tree/_criterion.cpython-311-darwin.so
causalml/inference/tree/_tree/_classes.py
causalml/inference/tree/_tree/_utils.cpp
causalml/inference/tree/_tree/_utils.pxd
causalml/inference/tree/_tree/_tree.pyx
causalml/inference/tree/causal/_builder.cpython-311-darwin.so
causalml/inference/tree/causal/causaltree.py
