Metadata-Version: 2.4
Name: causalml
Version: 0.15.5
Summary: Python Package for Uplift Modeling and Causal Inference with Machine Learning Algorithms
Author: Huigang Chen, Totte Harinen, Jeong-Yoon Lee, Jing Pan, Mike Yung, Zhenyu Zhao
Maintainer: Jeong-Yoon Lee
Project-URL: homepage, https://github.com/uber/causalml
Classifier: Programming Language :: Python
Classifier: License :: OSI Approved :: Apache Software License
Classifier: Operating System :: OS Independent
Requires-Python: >=3.9
License-File: LICENSE
Requires-Dist: forestci==0.6
Requires-Dist: pathos==0.2.9
Requires-Dist: numpy>=1.18.5
Requires-Dist: scipy<1.16.0,>=1.4.1
Requires-Dist: matplotlib
Requires-Dist: pandas>=0.24.1
Requires-Dist: scikit-learn>=1.6.0
Requires-Dist: statsmodels>=0.9.0
Requires-Dist: seaborn
Requires-Dist: xgboost
Requires-Dist: pydotplus
Requires-Dist: tqdm
Requires-Dist: shap
Requires-Dist: dill
Requires-Dist: lightgbm
Requires-Dist: packaging
Requires-Dist: graphviz
Provides-Extra: test
Requires-Dist: pytest>=4.6; extra == "test"
Requires-Dist: pytest-cov>=4.0; extra == "test"
Provides-Extra: tf
Requires-Dist: tensorflow>=2.4.0; extra == "tf"
Provides-Extra: torch
Requires-Dist: torch; extra == "torch"
Requires-Dist: pyro-ppl; extra == "torch"
Dynamic: license-file
